Metadata-Version: 2.1
Name: number2PersianWord
Version: 0.0.1
Summary: A short summary about your package
Home-page: UNKNOWN
Author: Alireza Esrafili
Author-email: aesi1050@gmail.com
License: MIT
Keywords: number2PersianWord
Platform: UNKNOWN
License-File: Licenses
